use_logger/__init__.py
use_logger/formatters.py
use_logger/handlers.py
use_logger/intercept.py
use_logger/logger.py
use_logger-0.1.9.dist-info/METADATA
use_logger-0.1.9.dist-info/WHEEL
use_logger-0.1.9.dist-info/RECORD
