Metadata-Version: 2.1
Name: use-logger
Version: 0.1.9
Summary: 一个全局拦截日志并转为loguru日志的插件
Author: nowanti
Author-email: believel.y@qq.com
Requires-Python: >=3.7,<4.0
Classifier: Programming Language :: Python :: 3
Classifier: Programming Language :: Python :: 3.7
Classifier: Programming Language :: Python :: 3.8
Classifier: Programming Language :: Python :: 3.9
Classifier: Programming Language :: Python :: 3.10
Classifier: Programming Language :: Python :: 3.11
Classifier: Programming Language :: Python :: 3.12
Requires-Dist: loguru (>=0,<1)
